restframework_datachange/__init__.py
restframework_datachange/model_maker.py
restframework_datachange/viewsets.py
restframework_datachange-0.0.2.1.dist-info/LICENSE
restframework_datachange-0.0.2.1.dist-info/METADATA
restframework_datachange-0.0.2.1.dist-info/WHEEL
restframework_datachange-0.0.2.1.dist-info/top_level.txt
restframework_datachange-0.0.2.1.dist-info/RECORD
