Metadata-Version: 2.1
Name: restframework-datachange
Version: 0.0.2.1
Summary: Change data in ModelViewSet
Home-page: https://github.com/RonDingDing/restframework_datachange
Author: Ron Ding
Author-email: ronweasleyding@163.com
License: Anti 996 License
Platform: UNKNOWN
Requires-Dist: django (>=2.1.7)
Requires-Dist: djangorestframework (>=3.9.1)
